{"timestamp": 29165, "groups": [{"distance": 0, "gap": "+0:00", "athletes": [{"hr": "", "pow": "", "bib": 303, "rank": 1, "IRM": "", "gname": "DAMIEN", "lat": 46.36130226156883, "nationality": "SUI", "spd": "20.47 kmh", "lon": 6.198767058827595, "valid": 1, "fname": "FORTIS", "team": "U17", "cad": ""}, {"hr": "133", "pow": "0", "bib": 302, "rank": 2, "IRM": "", "gname": "GABRIELE", "lat": 46.36130748255098, "nationality": "SUI", "spd": "21.87 kmh", "lon": 6.198770862537138, "valid": 1, "fname": "CERATO", "team": "U17", "cad": "75"}, {"hr": "135", "pow": "", "bib": 307, "rank": 3, "IRM": "", "gname": "Z\u00c9ON", "lat": 46.36131856709767, "nationality": "SUI", "spd": "20.88 kmh", "lon": 6.19877893810509, "valid": 1, "fname": "TAILLEFERT", "team": "U17", "cad": ""}, {"hr": "135", "pow": "0", "bib": 305, "rank": 4, "IRM": "", "gname": "HENRY", "lat": 46.361321619364155, "nationality": "GBR", "spd": "21.83 kmh", "lon": 6.198781161812208, "valid": 1, "fname": "LAWTON", "team": "U17", "cad": "69"}, {"hr": "140", "pow": "0", "bib": 306, "rank": 5, "IRM": "", "gname": "THIBAUD", "lat": 46.36133358746167, "nationality": "SUI", "spd": "21.20 kmh", "lon": 6.198789881084853, "valid": 1, "fname": "ROSSIER", "team": "U17", "cad": "72"}, {"hr": "", "pow": "", "bib": 301, "rank": 6, "IRM": "", "gname": "SYLVAIN", "lat": 46.361351981383365, "nationality": "SUI", "spd": "21.02 kmh", "lon": 6.198803281846166, "valid": 1, "fname": "BRUNNER", "team": "U17", "cad": ""}, {"hr": "", "pow": "", "bib": 304, "rank": 7, "IRM": "", "gname": "MAXIME", "lat": 46.36135929075836, "nationality": "SUI", "spd": "21.84 kmh", "lon": 6.198808607039526, "valid": 1, "fname": "JUILLERAT", "team": "U17", "cad": ""}, {"hr": "", "pow": "", "bib": 401, "rank": 8, "IRM": "", "gname": "MARGOT", "lat": 46.36140820734487, "nationality": "SUI", "spd": "22.48 kmh", "lon": 6.198844244872013, "valid": 1, "fname": "VESIN", "team": "W17", "cad": ""}], "no": 1}]}