{"timestamp": 29565, "groups": [{"distance": 0, "gap": "+0:00", "athletes": [{"hr": "188", "pow": "0", "bib": 305, "rank": 1, "IRM": "", "gname": "HENRY", "lat": 46.374633506707674, "nationality": "GBR", "spd": "42.57 kmh", "lon": 6.194110741393582, "valid": 1, "fname": "LAWTON", "team": "U17", "cad": "81"}, {"hr": "197", "pow": "0", "bib": 302, "rank": 2, "IRM": "", "gname": "GABRIELE", "lat": 46.37462772841901, "nationality": "SUI", "spd": "44.73 kmh", "lon": 6.194046555216902, "valid": 1, "fname": "CERATO", "team": "U17", "cad": "89"}, {"hr": "171", "pow": "", "bib": 307, "rank": 3, "IRM": "", "gname": "Z\u00c9ON", "lat": 46.37463184253437, "nationality": "SUI", "spd": "42.72 kmh", "lon": 6.193988369871061, "valid": 1, "fname": "TAILLEFERT", "team": "U17", "cad": ""}, {"hr": "", "pow": "", "bib": 303, "rank": 4, "IRM": "", "gname": "DAMIEN", "lat": 46.37463352207861, "nationality": "SUI", "spd": "42.20 kmh", "lon": 6.193969730966059, "valid": 1, "fname": "FORTIS", "team": "U17", "cad": ""}, {"hr": "", "pow": "", "bib": 301, "rank": 5, "IRM": "", "gname": "SYLVAIN", "lat": 46.37463950994931, "nationality": "SUI", "spd": "42.64 kmh", "lon": 6.193943706758778, "valid": 1, "fname": "BRUNNER", "team": "U17", "cad": ""}, {"hr": "183", "pow": "0", "bib": 306, "rank": 6, "IRM": "", "gname": "THIBAUD", "lat": 46.374659579662065, "nationality": "SUI", "spd": "43.02 kmh", "lon": 6.193856101689692, "valid": 1, "fname": "ROSSIER", "team": "U17", "cad": "107"}, {"hr": "", "pow": "", "bib": 304, "rank": 7, "IRM": "", "gname": "MAXIME", "lat": 46.37466924423139, "nationality": "SUI", "spd": "41.64 kmh", "lon": 6.193807778843045, "valid": 1, "fname": "JUILLERAT", "team": "U17", "cad": ""}], "no": 1}, {"distance": 250, "gap": "+0:23", "athletes": [{"hr": "", "pow": "", "bib": 401, "rank": 8, "IRM": "", "gname": "MARGOT", "lat": 46.37480506406202, "nationality": "SUI", "spd": "38.95 kmh", "lon": 6.191273563877482, "valid": 1, "fname": "VESIN", "team": "W17", "cad": ""}], "no": 2}]}