{"timestamp": 29670, "groups": [{"distance": 0, "gap": "+0:00", "athletes": [{"hr": "178", "pow": "0", "bib": 305, "rank": 1, "IRM": "", "gname": "HENRY", "lat": 46.37615176086248, "nationality": "GBR", "spd": "44.20 kmh", "lon": 6.208663479079543, "valid": 1, "fname": "LAWTON", "team": "U17", "cad": "0"}, {"hr": "175", "pow": "0", "bib": 306, "rank": 2, "IRM": "", "gname": "THIBAUD", "lat": 46.37619192958403, "nationality": "SUI", "spd": "47.69 kmh", "lon": 6.208641706326232, "valid": 1, "fname": "ROSSIER", "team": "U17", "cad": "109"}, {"hr": "182", "pow": "", "bib": 307, "rank": 3, "IRM": "", "gname": "Z\u00c9ON", "lat": 46.37619503085403, "nationality": "SUI", "spd": "58.96 kmh", "lon": 6.208639959633937, "valid": 1, "fname": "TAILLEFERT", "team": "U17", "cad": ""}, {"hr": "", "pow": "", "bib": 301, "rank": 4, "IRM": "", "gname": "SYLVAIN", "lat": 46.37620223921131, "nationality": "SUI", "spd": "41.96 kmh", "lon": 6.208635899754548, "valid": 1, "fname": "BRUNNER", "team": "U17", "cad": ""}, {"hr": "", "pow": "", "bib": 304, "rank": 5, "IRM": "", "gname": "MAXIME", "lat": 46.376255659390864, "nationality": "SUI", "spd": "45.05 kmh", "lon": 6.208605257499587, "valid": 1, "fname": "JUILLERAT", "team": "U17", "cad": ""}, {"hr": "189", "pow": "0", "bib": 302, "rank": 6, "IRM": "", "gname": "GABRIELE", "lat": 46.37626010388268, "nationality": "SUI", "spd": "46.63 kmh", "lon": 6.208602318400164, "valid": 0, "fname": "CERATO", "team": "U17", "cad": "0"}, {"hr": "", "pow": "", "bib": 303, "rank": 7, "IRM": "", "gname": "DAMIEN", "lat": 46.376291160791716, "nationality": "SUI", "spd": "45.96 kmh", "lon": 6.208581780766768, "valid": 0, "fname": "FORTIS", "team": "U17", "cad": ""}], "no": 1}, {"distance": 477, "gap": "+0:39", "athletes": [{"hr": "", "pow": "", "bib": 401, "rank": 8, "IRM": "", "gname": "MARGOT", "lat": 46.37871894372012, "nationality": "SUI", "spd": "22.93 kmh", "lon": 6.203823517500739, "valid": 0, "fname": "VESIN", "team": "W17", "cad": ""}], "no": 2}]}