{"timestamp": 29735, "groups": [{"distance": 0, "gap": "+0:00", "athletes": [{"hr": "", "pow": "", "bib": 301, "rank": 1, "IRM": "", "gname": "SYLVAIN", "lat": 46.371708450390265, "nationality": "SUI", "spd": "30.49 kmh", "lon": 6.2072357996795, "valid": 1, "fname": "BRUNNER", "team": "U17", "cad": ""}, {"hr": "162", "pow": "72", "bib": 306, "rank": 2, "IRM": "", "gname": "THIBAUD", "lat": 46.37170889675873, "nationality": "SUI", "spd": "32.67 kmh", "lon": 6.207235879886335, "valid": 1, "fname": "ROSSIER", "team": "U17", "cad": "86"}, {"hr": "", "pow": "", "bib": 303, "rank": 3, "IRM": "", "gname": "DAMIEN", "lat": 46.371709432400905, "nationality": "SUI", "spd": "26.08 kmh", "lon": 6.207235976134537, "valid": 1, "fname": "FORTIS", "team": "U17", "cad": ""}, {"hr": "164", "pow": "63", "bib": 305, "rank": 4, "IRM": "", "gname": "HENRY", "lat": 46.371744784783914, "nationality": "GBR", "spd": "26.33 kmh", "lon": 6.20724232851586, "valid": 1, "fname": "LAWTON", "team": "U17", "cad": "86"}, {"hr": "168", "pow": "35", "bib": 302, "rank": 5, "IRM": "", "gname": "GABRIELE", "lat": 46.371750587574056, "nationality": "SUI", "spd": "26.67 kmh", "lon": 6.207243371204713, "valid": 1, "fname": "CERATO", "team": "U17", "cad": "82"}, {"hr": "", "pow": "", "bib": 304, "rank": 6, "IRM": "", "gname": "MAXIME", "lat": 46.371796831347794, "nationality": "SUI", "spd": "30.71 kmh", "lon": 6.207251680632806, "valid": 0, "fname": "JUILLERAT", "team": "U17", "cad": ""}, {"hr": "172", "pow": "", "bib": 307, "rank": 7, "IRM": "", "gname": "Z\u00c9ON", "lat": 46.37180102721143, "nationality": "SUI", "spd": "26.63 kmh", "lon": 6.207252434577055, "valid": 0, "fname": "TAILLEFERT", "team": "U17", "cad": ""}], "no": 1}, {"distance": 383, "gap": "+0:51", "athletes": [{"hr": "", "pow": "", "bib": 401, "rank": 8, "IRM": "", "gname": "MARGOT", "lat": 46.37504950738242, "nationality": "SUI", "spd": "24.76 kmh", "lon": 6.208454629066923, "valid": 1, "fname": "VESIN", "team": "W17", "cad": ""}], "no": 2}]}